quantag/__init__.py
quantag/qaoa/__init__.py
quantag/qaoa/solver.py
quantag/qimage/__init__.py
quantag/qimage/compression.py
quantag/qimage/utils.py
quantag/vm/__init__.py
quantag/vm/backend.py
quantag/vm/version.py
quantag-0.5.0.dist-info/licenses/LICENSE
quantag-0.5.0.dist-info/METADATA
quantag-0.5.0.dist-info/WHEEL
quantag-0.5.0.dist-info/top_level.txt
quantag-0.5.0.dist-info/RECORD
