Metadata-Version: 2.4
Name: quantag
Version: 0.5.0
Summary: Quantag Quantum Virtual Machine backend for Qiskit
Author-email: Quantag IT Solutions GmbH <info@quantag-it.com>
License: MIT License
Project-URL: Homepage, https://quantum.quantag-it.com
Project-URL: Source, https://github.com/quantag/quantag-python
Keywords: quantum,qiskit,simulator,cudaq
Classifier: Programming Language :: Python :: 3
Classifier: License :: OSI Approved :: MIT License
Classifier: Operating System :: OS Independent
Classifier: Topic :: Scientific/Engineering :: Physics
Requires-Python: >=3.8
License-File: LICENSE
Requires-Dist: qiskit<2.0.0,>=1.0.0
Requires-Dist: qiskit-optimization>=0.6.0
Requires-Dist: pandas>=2.0.0
Requires-Dist: requests>=2.0.0
Requires-Dist: numpy>=1.20
Requires-Dist: Pillow>=9.0
Provides-Extra: dwave
Requires-Dist: dwave-ocean-sdk>=6.5.0; extra == "dwave"
Dynamic: license-file
